dagster_huaweicloud/__init__.py
dagster_huaweicloud/obs/__init__.py
dagster_huaweicloud/obs/compute_log_manager.py
dagster_huaweicloud/obs/file_manager.py
dagster_huaweicloud/obs/io_manager.py
dagster_huaweicloud/obs/resources.py
dagster_huaweicloud/obs/util.py
dagster_huaweicloud-1.0.0.dist-info/METADATA
dagster_huaweicloud-1.0.0.dist-info/WHEEL
dagster_huaweicloud-1.0.0.dist-info/top_level.txt
dagster_huaweicloud-1.0.0.dist-info/RECORD
