Metadata-Version: 2.1
Name: dagster-huaweicloud
Version: 1.0.0
Summary: Package for Huaweicloud-specific Dagster framework solid and resource components
Home-page: https://gitee.com/HuaweiCloudDeveloper/huaweicloud-dagster-components-python
Author: HuaweiCloud
Author-email: 
License: OSI Approved :: Apache Software License
Keywords: dagster
Requires-Python: >=3.9
Requires-Dist: pydantic ==1.10.11
Requires-Dist: esdk-obs-python
Requires-Dist: dagster
